matematica/__init__.py
matematica/aritmetica.py
matematica/geometria.py
afoonematematica-0.1.dist-info/LICENSE.txt
afoonematematica-0.1.dist-info/METADATA
afoonematematica-0.1.dist-info/WHEEL
afoonematematica-0.1.dist-info/top_level.txt
afoonematematica-0.1.dist-info/RECORD
