Metadata-Version: 2.1
Name: afoonematematica
Version: 0.1
Summary: Librería matemática para la clase de python avanzado
Home-page: http://my-repo.example.com
Author: Alfonso Tienda
Author-email: afoone@hotmail.com
License: MIT
Platform: UNKNOWN
Classifier: Development Status :: 3 - Alpha
Classifier: Intended Audience :: Education
Classifier: License :: OSI Approved :: MIT License
Classifier: Operating System :: OS Independent
Classifier: Programming Language :: Python :: 3
Requires-Python: >=3.0
License-File: LICENSE.txt
